daytona_sdk/__init__.py
daytona_sdk/_async/__init__.py
daytona_sdk/_async/code_interpreter.py
daytona_sdk/_async/computer_use.py
daytona_sdk/_async/daytona.py
daytona_sdk/_async/filesystem.py
daytona_sdk/_async/git.py
daytona_sdk/_async/lsp_server.py
daytona_sdk/_async/object_storage.py
daytona_sdk/_async/process.py
daytona_sdk/_async/sandbox.py
daytona_sdk/_async/snapshot.py
daytona_sdk/_async/volume.py
daytona_sdk/_sync/__init__.py
daytona_sdk/_sync/code_interpreter.py
daytona_sdk/_sync/computer_use.py
daytona_sdk/_sync/daytona.py
daytona_sdk/_sync/filesystem.py
daytona_sdk/_sync/git.py
daytona_sdk/_sync/lsp_server.py
daytona_sdk/_sync/object_storage.py
daytona_sdk/_sync/process.py
daytona_sdk/_sync/sandbox.py
daytona_sdk/_sync/snapshot.py
daytona_sdk/_sync/volume.py
daytona_sdk/_utils/__init__.py
daytona_sdk/_utils/deprecation.py
daytona_sdk/_utils/docs_ignore.py
daytona_sdk/_utils/enum.py
daytona_sdk/_utils/environment.py
daytona_sdk/_utils/errors.py
daytona_sdk/_utils/stream.py
daytona_sdk/_utils/timeout.py
daytona_sdk/_utils/types.py
daytona_sdk/code_toolbox/__init__.py
daytona_sdk/code_toolbox/sandbox_js_code_toolbox.py
daytona_sdk/code_toolbox/sandbox_python_code_toolbox.py
daytona_sdk/code_toolbox/sandbox_ts_code_toolbox.py
daytona_sdk/common/__init__.py
daytona_sdk/common/charts.py
daytona_sdk/common/code_interpreter.py
daytona_sdk/common/computer_use.py
daytona_sdk/common/daytona.py
daytona_sdk/common/errors.py
daytona_sdk/common/filesystem.py
daytona_sdk/common/git.py
daytona_sdk/common/image.py
daytona_sdk/common/lsp_server.py
daytona_sdk/common/process.py
daytona_sdk/common/protocols.py
daytona_sdk/common/pty.py
daytona_sdk/common/sandbox.py
daytona_sdk/common/snapshot.py
daytona_sdk/common/volume.py
daytona_sdk/handle/async_pty_handle.py
daytona_sdk/handle/pty_handle.py
daytona_sdk/internal/__init__.py
daytona_sdk/internal/toolbox_api_client_proxy.py
daytona_sdk/py.typed
daytona_sdk-0.138.0.dist-info/LICENSE
daytona_sdk-0.138.0.dist-info/METADATA
daytona_sdk-0.138.0.dist-info/WHEEL
daytona_sdk-0.138.0.dist-info/RECORD
