Metadata-Version: 2.3
Name: daytona_sdk
Version: 0.138.0
Summary: Python SDK for Daytona
License: Apache-2.0
Keywords: daytona,sdk
Author: Daytona Platforms Inc.
Author-email: support@daytona.io
Requires-Python: >=3.9,<4.0
Classifier: Development Status :: 3 - Alpha
Classifier: Intended Audience :: Developers
Classifier: Programming Language :: Python :: 3
Classifier: Programming Language :: Python :: 3.9
Classifier: Programming Language :: Python :: 3.10
Classifier: Programming Language :: Python :: 3.11
Classifier: Programming Language :: Python :: 3.12
Classifier: Programming Language :: Python :: 3.13
Classifier: Programming Language :: Python :: 3.14
Requires-Dist: Deprecated (>=1.2.18,<2.0.0)
Requires-Dist: aiofiles (>=24.1.0,<24.2.0)
Requires-Dist: daytona-api-client (==0.138.0)
Requires-Dist: daytona-api-client-async (==0.138.0)
Requires-Dist: daytona-toolbox-api-client (==0.138.0)
Requires-Dist: daytona-toolbox-api-client-async (==0.138.0)
Requires-Dist: environs (>=10.0.0,<15.0.0)
Requires-Dist: httpx (>=0.28.0,<0.29.0)
Requires-Dist: multipart (>=1.0.0,<2.0.0)
Requires-Dist: obstore (>=0.8.0,<0.9.0)
Requires-Dist: pydantic (>=2.4.2,<3.0.0)
Requires-Dist: toml (>=0.10.0,<0.11.0)
Requires-Dist: typing-extensions (>=4.0.0) ; python_version < "3.10"
Requires-Dist: websockets (>=15.0.0,<16.0.0)
